LICENSE
MANIFEST.in
README.md
requirements.txt
setup.py
examples/__init__.py
examples/transceiver.py
smpp/__init__.py
smpp.twisted3.egg-info/PKG-INFO
smpp.twisted3.egg-info/SOURCES.txt
smpp.twisted3.egg-info/dependency_links.txt
smpp.twisted3.egg-info/not-zip-safe
smpp.twisted3.egg-info/requires.txt
smpp.twisted3.egg-info/top_level.txt
smpp/twisted/__init__.py
smpp/twisted/client.py
smpp/twisted/config.py
smpp/twisted/protocol.py
smpp/twisted/server.py
tests/test_smpp_client.py
tests/test_smpp_protocol.py
tests/test_smpp_server.py