Metadata-Version: 2.1
Name: smpp.twisted3
Version: 0.8
Summary: SMPP 3.4 client built on Twisted / Python3
Home-page: https://github.com/jookies/smpp.twisted
Author: Roger Hoover
Author-email: roger.hoover@gmail.com
License: Apache License 2.0
Keywords: smpp twisted
Classifier: Development Status :: 5 - Production/Stable
Classifier: Framework :: Twisted
Classifier: Topic :: System :: Networking
Classifier: Operating System :: OS Independent
Classifier: License :: OSI Approved :: Apache Software License
Classifier: Intended Audience :: Developers
Classifier: Programming Language :: Python
Classifier: Programming Language :: Python :: 3
Classifier: Programming Language :: Python :: 3.5
Classifier: Programming Language :: Python :: 3.6
Classifier: Programming Language :: Python :: 3.7
Classifier: Programming Language :: Python :: 3.8
Classifier: Topic :: Software Development :: Libraries :: Python Modules
License-File: LICENSE
Requires-Dist: Twisted~=23.10.0
Requires-Dist: smpp.pdu3~=0.4
